mmumu/__init__.py
mmumu/api.py
mmumu/base.py
mmumu/manger.py
mmumu-0.0.2.dist-info/METADATA
mmumu-0.0.2.dist-info/WHEEL
mmumu-0.0.2.dist-info/top_level.txt
mmumu-0.0.2.dist-info/RECORD
