Metadata-Version: 2.1
Name: mmumu
Version: 0.0.2
Summary: Mumu12模拟器工具
Author: KateTseng
Author-email: Kate.TsengK@outlook.com
License: MIT
Keywords: Auto Script Testing
Requires-Python: >=3
